pyhanko/__main__.py
pyhanko/cli/__init__.py
pyhanko/cli/_ctx.py
pyhanko/cli/_root.py
pyhanko/cli/_trust.py
pyhanko/cli/cache.py
pyhanko/cli/config.py
pyhanko/cli/plugin_api.py
pyhanko/cli/py.typed
pyhanko/cli/runtime.py
pyhanko/cli/utils.py
pyhanko/cli/version.py
pyhanko/cli/commands/__init__.py
pyhanko/cli/commands/crypt.py
pyhanko/cli/commands/fields.py
pyhanko/cli/commands/stamp.py
pyhanko/cli/commands/signing/__init__.py
pyhanko/cli/commands/signing/pkcs11_cli.py
pyhanko/cli/commands/signing/plugin.py
pyhanko/cli/commands/signing/simple.py
pyhanko/cli/commands/signing/utils.py
pyhanko/cli/commands/validation/__init__.py
pyhanko/cli/commands/validation/ltv.py
pyhanko/cli/commands/validation/validate.py
pyhanko_cli-0.2.0.dist-info/licenses/LICENSE
pyhanko_cli-0.2.0.dist-info/METADATA
pyhanko_cli-0.2.0.dist-info/WHEEL
pyhanko_cli-0.2.0.dist-info/entry_points.txt
pyhanko_cli-0.2.0.dist-info/top_level.txt
pyhanko_cli-0.2.0.dist-info/RECORD
