Metadata-Version: 2.4
Name: pyhanko-cli
Version: 0.2.0
Summary: CLI tools for stamping and signing PDF files
Author-email: Matthias Valvekens <dev@mvalvekens.be>
Maintainer-email: Matthias Valvekens <dev@mvalvekens.be>
License-Expression: MIT
Project-URL: Homepage, https://github.com/MatthiasValvekens/pyHanko
Project-URL: Documentation, https://docs.pyhanko.eu/
Project-URL: Changes, https://docs.pyhanko.eu/en/latest/changelog.html
Project-URL: Source Code, https://github.com/MatthiasValvekens/pyHanko
Project-URL: Issue Tracker, https://github.com/MatthiasValvekens/pyHanko/issues
Keywords: signature,pdf,pades,digital-signature,pkcs11
Classifier: Development Status :: 4 - Beta
Classifier: Intended Audience :: Developers
Classifier: Operating System :: OS Independent
Classifier: Programming Language :: Python :: 3
Classifier: Programming Language :: Python :: 3.9
Classifier: Programming Language :: Python :: 3.10
Classifier: Programming Language :: Python :: 3.11
Classifier: Programming Language :: Python :: 3.12
Classifier: Programming Language :: Python :: 3.13
Classifier: Topic :: Security :: Cryptography
Classifier: Topic :: Software Development :: Libraries :: Python Modules
Requires-Python: >=3.9
License-File: LICENSE
Requires-Dist: asn1crypto>=1.5.1
Requires-Dist: tzlocal>=4.3
Requires-Dist: pyhanko<0.32,>=0.31.0
Requires-Dist: pyhanko-certvalidator<0.30,>=0.29.0
Requires-Dist: click!=8.2.0,>=8.1.3
Requires-Dist: platformdirs>=4.3.8
Dynamic: license-file
